[
  {
    "id": "executive-os",
    "name": "Executive OS & Planning",
    "description": "Constraint-based planning, weekly rhythm, life operations."
  },
  {
    "id": "accountability",
    "name": "Accountability & Consistency",
    "description": "Stop restarting; build self-trust and follow-through."
  },
  {
    "id": "burnout-recovery",
    "name": "Overwhelm & Recovery",
    "description": "Burnout, overwhelm, capacity rebuild, minimum viable day."
  },
  {
    "id": "systems-decisions",
    "name": "Systems Thinking & Decisions",
    "description": "Decision-making, constraints, leverage, feedback loops."
  },
  {
    "id": "coaching-standards",
    "name": "Coaching & Standards",
    "description": "What coaching is, standards vs perfectionism, calm ambition."
  },
  {
    "id": "ai-support",
    "name": "AI Support & Chief of Staff",
    "description": "AI assistant, AI chief of staff, AI accountability; careful capture of 'AI therapist' queries."
  }
]